[
  {
    "name": "하숙영가마솥비빔밥",
    "address": "전북특별자치도 전주시 완산구 중앙동3가 78-1 하숙영가마솥비빔밥",
    "category": "비빔밥"
  },
  {
    "name": "풍남정",
    "address": "전북특별자치도 전주시 완산구 전동 71-1",
    "category": "비빔밥"
  },
  {
    "name": "호남각",
    "address": "전북특별자치도 전주시 덕진구 송천동2가 560-5 호남각",
    "category": "비빔밥"
  },
  {
    "name": "백송회관",
    "address": "전북특별자치도 전주시 완산구 서노송동 568-133",
    "category": "비빔밥"
  },
  {
    "name": "한국관 본점",
    "address": "전북특별자치도 전주시 덕진구 금암동 712-3",
    "category": "비빔밥"
  },
  {
    "name": "전주왱이콩나물국밥전문점",
    "address": "전북특별자치도 전주시 완산구 경원동2가 12-1",
    "category": "콩나물국밥"
  },
  {
    "name": "현대옥 전주본점",
    "address": "전북특별자치도 전주시 완산구 중화산동2가 757-3",
    "category": "콩나물국밥"
  },
  {
    "name": "삼백집 전주 본점",
    "address": "전북특별자치도 전주시 완산구 고사동 454-1",
    "category": "콩나물국밥"
  },
  {
    "name": "현대옥 남부시장점",
    "address": "전북특별자치도 전주시 완산구 전동3가 2-242",
    "category": "콩나물국밥"
  },
  {
    "name": "금양정 전주본점",
    "address": "전북특별자치도 전주시 완산구 중화산동2가 200-1",
    "category": "한정식"
  },
  {
    "name": "한울밥상",
    "address": "전북특별자치도 전주시 완산구 남노송동 529-21",
    "category": "한정식"
  },
  {
    "name": "녹두꽃",
    "address": "전북특별자치도 전주시 완산구 전동 211-3 한옥마을 주차장 안쪽 1층",
    "category": "한정식"
  },
  {
    "name": "양반가",
    "address": "전북특별자치도 전주시 완산구 풍남동3가 79-2",
    "category": "한정식"
  },
  {
    "name": "고궁담",
    "address": "전북특별자치도 전주시 완산구 효자동3가 1627-1 2~3층",
    "category": "한정식"
  },
  {
    "name": "베테랑 칼국수",
    "address": "전북특별자치도 전주시 완산구 교동 84-10",
    "category": "칼국수"
  },
  {
    "name": "솝말칼국수 전주역점",
    "address": "전북특별자치도 전주시 덕진구 호성동1가 699-2 솝말칼국수 전주역점",
    "category": "칼국수"
  },
  {
    "name": "남촌칼국수",
    "address": "전북특별자치도 전주시 완산구 효자동3가 1696-7 1층",
    "category": "칼국수"
  },
  {
    "name": "베테랑 신시가지점",
    "address": "전북특별자치도 전주시 완산구 효자동2가 1227-3 세움 펠리피아 오피스텔",
    "category": "칼국수"
  },
  {
    "name": "금암면옥 본점",
    "address": "전북특별자치도 전주시 덕진구 금암동 471-10",
    "category": "칼국수"
  },
  {
    "name": "몽유도 신시가지점",
    "address": "전북특별자치도 전주시 완산구 효자동3가 1527-10 1층",
    "category": "삼겹살"
  },
  {
    "name": "고향역 전주객사본점",
    "address": "전북특별자치도 전주시 완산구 다가동4가 125-1 1층",
    "category": "삼겹살"
  },
  {
    "name": "몽유도 전주본점",
    "address": "전북특별자치도 전주시 완산구 다가동3가 6-1",
    "category": "삼겹살"
  },
  {
    "name": "다가생구이 본점",
    "address": "전북특별자치도 전주시 완산구 고사동 462-9",
    "category": "삼겹살"
  },
  {
    "name": "오일내 전북대점",
    "address": "전북특별자치도 전주시 덕진구 덕진동1가 1314-179 2층",
    "category": "삼겹살"
  },
  {
    "name": "해율담",
    "address": "전북특별자치도 전주시 완산구 경원동3가 15-5 1층, 2층",
    "category": "한우"
  },
  {
    "name": "대장간 서신점",
    "address": "전북특별자치도 전주시 완산구 서신동 937-1 1층",
    "category": "한우"
  },
  {
    "name": "호성정 정육식당",
    "address": "전북특별자치도 전주시 덕진구 호성동1가 785-1 1층 호성정 정육식당",
    "category": "한우"
  },
  {
    "name": "명가등심",
    "address": "전북특별자치도 전주시 완산구 효자동3가 1698-6",
    "category": "한우"
  },
  {
    "name": "우백갈비 아중리본점",
    "address": "전북특별자치도 전주시 덕진구 우아동1가 1114-2 해달별 1층",
    "category": "한우"
  },
  {
    "name": "노벨반점",
    "address": "전북특별자치도 전주시 완산구 전동3가 157-1",
    "category": "중화요리"
  },
  {
    "name": "독립군",
    "address": "전북특별자치도 전주시 완산구 중화산동2가 663-7 1층",
    "category": "중화요리"
  },
  {
    "name": "진미반점",
    "address": "전북특별자치도 전주시 완산구 중앙동2가 44-1",
    "category": "중화요리"
  },
  {
    "name": "수정관",
    "address": "전북특별자치도 전주시 완산구 서노송동 604",
    "category": "중화요리"
  },
  {
    "name": "치히로",
    "address": "전북특별자치도 전주시 완산구 고사동 324-15",
    "category": "일식"
  },
  {
    "name": "진담동&소바 전주효자동신시가지본점",
    "address": "전북특별자치도 전주시 완산구 효자동3가 1534-5 103호",
    "category": "일식"
  },
  {
    "name": "정동 전주객사점",
    "address": "전북특별자치도 전주시 완산구 고사동 371 1층",
    "category": "일식"
  },
  {
    "name": "치히로 전북대점",
    "address": "전북특별자치도 전주시 덕진구 금암동 664-48",
    "category": "일식"
  },
  {
    "name": "동락",
    "address": "전북특별자치도 전주시 완산구 중앙동3가 88-1 동락",
    "category": "일식"
  },
  {
    "name": "스시아시타 송천",
    "address": "전북특별자치도 전주시 덕진구 송천동2가 492-1 1층 입구건물",
    "category": "초밥"
  },
  {
    "name": "마와루스시 전주효자",
    "address": "전북특별자치도 전주시 완산구 효자동3가 1648-1 1층 103, 104호",
    "category": "초밥"
  },
  {
    "name": "가라스시 회전초밥 중화산점",
    "address": "전북특별자치도 전주시 완산구 중화산동2가 268 1층 102호",
    "category": "초밥"
  },
  {
    "name": "마와루스시 전주아중",
    "address": "전북특별자치도 전주시 덕진구 인후동1가 404-3 1층 101호",
    "category": "초밥"
  },
  {
    "name": "코토리",
    "address": "전북특별자치도 전주시 완산구 중앙동4가 7-2 1층",
    "category": "초밥"
  },
  {
    "name": "영등동골목길",
    "address": "전북특별자치도 전주시 완산구 효자동3가 1630-4 1층",
    "category": "이탈리안"
  },
  {
    "name": "양식당",
    "address": "전북특별자치도 전주시 완산구 전동 110-1 1층",
    "category": "이탈리안"
  },
  {
    "name": "비스트로준",
    "address": "전북특별자치도 전주시 완산구 효자동3가 1544-3 101동 1층 101호",
    "category": "이탈리안"
  },
  {
    "name": "로쏘파스타바",
    "address": "전북특별자치도 전주시 완산구 다가동4가 49-1 로쏘파스타바",
    "category": "이탈리안"
  },
  {
    "name": "핸더 아중점",
    "address": "전북특별자치도 전주시 덕진구 우아동2가 934-10 101호",
    "category": "이탈리안"
  },
  {
    "name": "제일제과",
    "address": "전북특별자치도 전주시 완산구 남노송동 540-6 제일제과",
    "category": "베이커리"
  },
  {
    "name": "온심당베이커리",
    "address": "전북특별자치도 전주시 완산구 중화산동2가 759-9 최재호베이커리",
    "category": "베이커리"
  },
  {
    "name": "송해븐",
    "address": "전북특별자치도 전주시 덕진구 만성동 1259-8 1층 SONGHEAVEN 송해븐",
    "category": "베이커리"
  },
  {
    "name": "우노스",
    "address": "전북특별자치도 전주시 덕진구 덕진동1가 1315-51 우노스",
    "category": "베이커리"
  },
  {
    "name": "크러스트",
    "address": "전북특별자치도 전주시 완산구 고사동 485-1",
    "category": "베이커리"
  },
  {
    "name": "풍년제과 본점",
    "address": "전북특별자치도 전주시 완산구 전동 100 풍년제과 본점",
    "category": "카페"
  },
  {
    "name": "PNB 풍년제과 본점",
    "address": "전북특별자치도 전주시 완산구 경원동1가 40-5",
    "category": "카페"
  },
  {
    "name": "카페이르리",
    "address": "전북특별자치도 전주시 완산구 교동 63-13",
    "category": "카페"
  },
  {
    "name": "평화와평화",
    "address": "전북특별자치도 전주시 완산구 중앙동3가 29 3층",
    "category": "카페"
  },
  {
    "name": "카츠모리조",
    "address": "전북특별자치도 전주시 완산구 중화산동2가 24-15 2층",
    "category": "돈까스"
  },
  {
    "name": "돈카츠흑심 본점",
    "address": "전북특별자치도 전주시 완산구 다가동3가 103-1 1층",
    "category": "돈까스"
  },
  {
    "name": "The담다",
    "address": "전북특별자치도 전주시 덕진구 덕진동1가 664-6 원플러스빌딩 1층",
    "category": "돈까스"
  },
  {
    "name": "돈카츠흑심 효자점",
    "address": "전북특별자치도 전주시 완산구 효자동2가 1239-1 104호 돈카츠흑심",
    "category": "돈까스"
  },
  {
    "name": "아리랑보쌈왕족발",
    "address": "전북특별자치도 전주시 완산구 삼천동1가 732-11",
    "category": "보쌈/족발"
  },
  {
    "name": "족떡이네",
    "address": "전북특별자치도 전주시 완산구 교동 64-8",
    "category": "보쌈/족발"
  },
  {
    "name": "황제보쌈",
    "address": "전북특별자치도 전주시 덕진구 덕진동1가 1264-10",
    "category": "보쌈/족발"
  },
  {
    "name": "옴그족발 전주 하가지구 본점",
    "address": "전북특별자치도 전주시 덕진구 덕진동2가 671-13 1층",
    "category": "보쌈/족발"
  },
  {
    "name": "만족왕족발보쌈",
    "address": "전북특별자치도 전주시 덕진구 송천동1가 265-46",
    "category": "보쌈/족발"
  },
  {
    "name": "전주 남부시장 한국닭집",
    "address": "전북특별자치도 전주시 완산구 전동3가 2-242",
    "category": "통닭"
  },
  {
    "name": "아리랑88통닭 아중점",
    "address": "전북특별자치도 전주시 덕진구 우아동2가 862-2 1층",
    "category": "통닭"
  },
  {
    "name": "아리랑88통닭송천점",
    "address": "전북특별자치도 전주시 덕진구 송천동2가 202-68",
    "category": "통닭"
  },
  {
    "name": "아리랑88통닭 전주평화점",
    "address": "전북특별자치도 전주시 완산구 평화동2가 888 1층 101호, 102호",
    "category": "통닭"
  },
  {
    "name": "금복통닭",
    "address": "전북특별자치도 전주시 덕진구 송천동2가 175-31 1층",
    "category": "통닭"
  },
  {
    "name": "연지본관",
    "address": "전북특별자치도 전주시 완산구 경원동3가 17-16 연지본관",
    "category": "갈비탕"
  },
  {
    "name": "연와미당",
    "address": "전북특별자치도 전주시 완산구 효자동1가 223-10",
    "category": "갈비탕"
  },
  {
    "name": "청학동들깨요리",
    "address": "전북특별자치도 전주시 완산구 중화산동2가 646-2 청학동들깨요리",
    "category": "갈비탕"
  },
  {
    "name": "청년매운갈비찜 전주본점",
    "address": "전북특별자치도 전주시 덕진구 장동 1088-4 청년매운갈비찜 전주본점",
    "category": "갈비탕"
  },
  {
    "name": "육일식당",
    "address": "전북특별자치도 전주시 완산구 삼천동2가 275-3",
    "category": "감자탕"
  },
  {
    "name": "무시로감자탕 만성점",
    "address": "전북특별자치도 전주시 덕진구 만성동 1262-10 101,102,103,104호",
    "category": "감자탕"
  },
  {
    "name": "무시로감자탕 본점",
    "address": "전북특별자치도 전주시 완산구 중화산동2가 658-7 1층",
    "category": "감자탕"
  },
  {
    "name": "양가네감자탕",
    "address": "전북특별자치도 전주시 덕진구 여의동2가 573-10",
    "category": "감자탕"
  },
  {
    "name": "해이루 전북대본점",
    "address": "전북특별자치도 전주시 덕진구 덕진동1가 1277-14 해이루",
    "category": "감자탕"
  },
  {
    "name": "조점례남문피순대",
    "address": "전북특별자치도 전주시 완산구 전동3가 2-240 조점례 남문피순대",
    "category": "국밥/탕류"
  },
  {
    "name": "정수진풍년순대 중화산본점",
    "address": "전북특별자치도 전주시 완산구 중화산동2가 755-7 1층 정수진풍년순대",
    "category": "국밥/탕류"
  },
  {
    "name": "현이네토종순대 전주효자동본점",
    "address": "전북특별자치도 전주시 완산구 효자동1가 622-7",
    "category": "국밥/탕류"
  },
  {
    "name": "금암피순대",
    "address": "전북특별자치도 전주시 덕진구 금암동 729-3",
    "category": "국밥/탕류"
  },
  {
    "name": "큰집피순대",
    "address": "전북특별자치도 전주시 덕진구 여의동2가 702-54",
    "category": "국밥/탕류"
  },
  {
    "name": "옛날땡땡이상추튀김",
    "address": "전북특별자치도 전주시 덕진구 금암동 664-39 1층중간",
    "category": "분식"
  },
  {
    "name": "동래분식",
    "address": "전북특별자치도 전주시 완산구 전동3가 2-240",
    "category": "분식"
  },
  {
    "name": "또또분식",
    "address": "전북특별자치도 전주시 덕진구 금암동 1545-1 또또분식",
    "category": "분식"
  },
  {
    "name": "경아분식",
    "address": "전북특별자치도 전주시 완산구 다가동3가 50-2",
    "category": "분식"
  },
  {
    "name": "떡두껍집 송천점",
    "address": "전북특별자치도 전주시 덕진구 송천동2가 202-47 1동 1층일부호",
    "category": "분식"
  },
  {
    "name": "오타마 전북대점",
    "address": "전북특별자치도 전주시 덕진구 덕진동1가 1277-10 오타마",
    "category": "술집"
  },
  {
    "name": "초로초로",
    "address": "전북특별자치도 전주시 완산구 다가동4가 55-6 1층",
    "category": "술집"
  },
  {
    "name": "숯토리 신시가지본점",
    "address": "전북특별자치도 전주시 완산구 효자동3가 1527-5 1층 103호",
    "category": "술집"
  },
  {
    "name": "그리다",
    "address": "전북특별자치도 전주시 완산구 효자동2가 1157-4 1층 131호 그리다",
    "category": "술집"
  },
  {
    "name": "미토",
    "address": "전북특별자치도 전주시 완산구 다가동4가 57-3 미토",
    "category": "술집"
  }
]